dgredis/__init__.py
dgredis/async_client.py
dgredis/conf.py
dgredis/decorator.py
dgredis/encoder.py
dgredis/py.typed
dgredis/sync_client.py
dgredis-1.0.1.dist-info/licenses/LICENSE
tests/__init__.py
tests/test_async_client.py
tests/test_auto_set_get.py
tests/test_context_manager.py
tests/test_db_index.py
tests/test_remove_key.py
dgredis-1.0.1.dist-info/METADATA
dgredis-1.0.1.dist-info/WHEEL
dgredis-1.0.1.dist-info/top_level.txt
dgredis-1.0.1.dist-info/RECORD
