Metadata-Version: 2.4
Name: dgredis
Version: 1.0.1
Summary: A convenient Redis client wrapper with JSON and datetime support.
Home-page: https://gitlab.com/gng-group/dgredis.git
Author: Malanris
Author-email: Roman Rasputin <admin@roro.su>
License: MIT License
Project-URL: Homepage, https://gitlab.com/gng-group/dgredis
Project-URL: BugTracker, https://gitlab.com/gng-group/dgredis/issues
Keywords: logging,logger,rotation,timed,advanced
Classifier: Development Status :: 4 - Beta
Classifier: Intended Audience :: Developers
Classifier: License :: OSI Approved :: MIT License
Classifier: Programming Language :: Python :: 3
Classifier: Programming Language :: Python :: 3.10
Classifier: Programming Language :: Python :: 3.11
Classifier: Programming Language :: Python :: 3.12
Classifier: Programming Language :: Python :: 3.13
Classifier: Operating System :: OS Independent
Classifier: Topic :: Software Development :: Libraries :: Python Modules
Classifier: Topic :: System :: Logging
Requires-Python: >=3.10
License-File: LICENSE
Requires-Dist: redis<8.0.0,>=7.1.0
Dynamic: author
Dynamic: home-page
Dynamic: license-file
